plone.app.referenceablebehavior-0.7.8-py2.7-nspkg.pth
plone/app/referenceablebehavior/__init__.py
plone/app/referenceablebehavior/configure.zcml
plone/app/referenceablebehavior/interfaces.py
plone/app/referenceablebehavior/profiles.zcml
plone/app/referenceablebehavior/rebuild_i18n.sh
plone/app/referenceablebehavior/referenceable.py
plone/app/referenceablebehavior/referenceable.rst
plone/app/referenceablebehavior/setuphandlers.py
plone/app/referenceablebehavior/subscribers.py
plone/app/referenceablebehavior/testing.py
plone/app/referenceablebehavior/uidcatalog.py
plone/app/referenceablebehavior/uidcatalog.rst
plone/app/referenceablebehavior/profiles/default/metadata.xml
plone/app/referenceablebehavior/profiles/default/referenceablebehavior.txt
plone/app/referenceablebehavior/profiles/default/toolset.xml
plone/app/referenceablebehavior/profiles/sample_types/archetype_tool.xml
plone/app/referenceablebehavior/profiles/sample_types/metadata.xml
plone/app/referenceablebehavior/profiles/sample_types/types.xml
plone/app/referenceablebehavior/profiles/sample_types/types/ATRefnode.xml
plone/app/referenceablebehavior/tests/__init__.py
plone/app/referenceablebehavior/tests/test_basics.py
plone/app/referenceablebehavior/tests/test_doctest.py
plone.app.referenceablebehavior-0.7.8.dist-info/METADATA
plone.app.referenceablebehavior-0.7.8.dist-info/WHEEL
plone.app.referenceablebehavior-0.7.8.dist-info/entry_points.txt
plone.app.referenceablebehavior-0.7.8.dist-info/namespace_packages.txt
plone.app.referenceablebehavior-0.7.8.dist-info/top_level.txt
plone.app.referenceablebehavior-0.7.8.dist-info/RECORD
