Metadata-Version: 2.1
Name: plone.app.referenceablebehavior
Version: 0.7.8
Summary: Referenceable dexterity type behavior
Home-page: http://plone.org/products/dexterity
Author: Plone Foundation
Author-email: mailto:dexterity-development@googlegroups.com
License: GPL
Keywords: dexterity referenceable plone
Platform: UNKNOWN
Classifier: Development Status :: 5 - Production/Stable
Classifier: Framework :: Plone
Classifier: Framework :: Plone :: 4.3
Classifier: Framework :: Plone :: 5.0
Classifier: Framework :: Plone :: 5.1
Classifier: Framework :: Plone :: 5.2
Classifier: Framework :: Plone :: Core
Classifier: License :: OSI Approved :: GNU General Public License (GPL)
Classifier: Programming Language :: Python
Classifier: Programming Language :: Python :: 2.6
Classifier: Programming Language :: Python :: 2.7
Classifier: Topic :: Software Development :: Libraries :: Python Modules
Requires-Dist: setuptools
Requires-Dist: plone.app.locales (>=4.3.9)
Requires-Dist: plone.behavior
Requires-Dist: plone.dexterity (>=1.1)
Requires-Dist: plone.indexer
Requires-Dist: plone.uuid
Requires-Dist: Products.Archetypes
Provides-Extra: test
Requires-Dist: Products.CMFPlone ; extra == 'test'
Requires-Dist: Products.Archetypes ; extra == 'test'
Requires-Dist: plone.app.testing ; extra == 'test'
Requires-Dist: plone.app.dexterity ; extra == 'test'
